SEQ/4-memory/4-memory.v
module SEQmemory(clk, icode, valA, valE, valP, valM);
    input clk;
    input [3:0] icode;
    input [63:0] valA, valE, valP;
    output reg [63:0] valM;

    reg [63:0] data_memory[2047:0];
    integer i;
    initial begin
        for(i = 0; i <= 50; i=i+1) begin
            data_memory[i] = i;
        end
    end

    always @(*) begin
         if (icode == 4'b0101) begin // mrmovq
            valM = data_memory[valE];
        end
        else if (icode == 4'b1001) begin // ret
            valM = data_memory[valA];
        end
        else if (icode == 4'b1011) begin // popq
            valM = data_memory[valA];
        end
    end
    always @(posedge clk) begin
       if (icode == 4'b0100) begin // rmmovq
            data_memory[valE] = valA;
       end
        else if (icode == 4'b1000) begin // call
            data_memory[valE] = valP;
        end
        else if (icode == 4'b1010) begin // pushq
            data_memory[valE] = valA;
        end
    end
endmodule

SEQ/4-memory/4-memory_tb.v
module memory_tb;
    reg clk;
    reg [3:0] icode;
    reg [63:0] valA, valE, valP;
    output [63:0] valM;

    SEQmemory DUT(clk, icode, valA, valE, valP, valM);
    initial begin
        $dumpfile("4-memory.vcd");
        $dumpvars(0, memory_tb);
        clk = 0;

        icode = 4'b0101; valE = 35; 
        #10 clk = ~clk; 
        #10 clk = ~clk;
        icode = 4'b1001; valA = 36; 
        #10 clk = ~clk; 
        #10 clk = ~clk;
        icode = 4'b1011; valA = 37; 
        #10 clk = ~clk; 
        #10 clk = ~clk;
        icode = 4'b0100;valE = 15; valA = 69; 
        #10 clk = ~clk; 
        #10 clk = ~clk;
        icode = 4'b1000;valE = 16; valP = 420;
        #10 clk = ~clk; 
        #10 clk = ~clk;
        icode = 4'b1010;valE = 17; valA = 500; 
        #10 clk = ~clk; 
        #10 clk = ~clk;
        icode = 4'b0101; valE = 15; 
        #10 clk = ~clk; 
        #10 clk = ~clk;
        icode = 4'b1001; valA = 16; 
        #10 clk = ~clk; 
        #10 clk = ~clk;
        icode = 4'b1011; valA = 17; 
        #10 clk = ~clk; 
        #10 clk = ~clk;
        
    end

    initial
        	$monitor("clk = %0d \tvalM = %0d \n",clk,valM);
endmodule

SEQ/4-memory/4-memory.vcd
$date
	Wed Mar  8 19:22:24 2023
$end
$version
	Icarus Verilog
$end
$timescale
	1s
$end
$scope module memory_tb $end
$var wire 64 ! valM [63:0] $end
$var reg 1 " clk $end
$var reg 4 # icode [3:0] $end
$var reg 64 $ valA [63:0] $end
$var reg 64 % valE [63:0] $end
$var reg 64 & valP [63:0] $end
$scope module DUT $end
$var wire 1 " clk $end
$var wire 4 ' icode [3:0] $end
$var wire 64 ( valA [63:0] $end
$var wire 64 ) valE [63:0] $end
$var wire 64 * valP [63:0] $end
$var reg 64 + valM [63:0] $end
$var integer 32 , i [31:0] $end
$upscope $end
$upscope $end
$enddefinitions $end
#0
$dumpvars
b110011 ,
b100011 +
bx *
b100011 )
bx (
b101 '
bx &
b100011 %
bx $
b101 #
0"
b100011 !
$end
#10
1"
#20
b100100 !
b100100 +
b100100 $
b100100 (
b1001 #
b1001 '
0"
#30
1"
#40
b100101 !
b100101 +
b100101 $
b100101 (
b1011 #
b1011 '
0"
#50
1"
#60
b1000101 $
b1000101 (
b1111 %
b1111 )
b100 #
b100 '
0"
#70
1"
#80
b110100100 &
b110100100 *
b10000 %
b10000 )
b1000 #
b1000 '
0"
#90
1"
#100
b111110100 $
b111110100 (
b10001 %
b10001 )
b1010 #
b1010 '
0"
#110
1"
#120
b1000101 !
b1000101 +
b1111 %
b1111 )
b101 #
b101 '
0"
#130
1"
#140
b110100100 !
b110100100 +
b10000 $
b10000 (
b1001 #
b1001 '
0"
#150
1"
#160
b111110100 !
b111110100 +
b10001 $
b10001 (
b1011 #
b1011 '
0"
