SEQ/2-decode/2-decode.v
module SEQdecode(clk, icode, rA, rB, valA, valB);
    input clk;
    input [3:0] icode, rA, rB;
    output reg [63:0] valA, valB;

    initial begin
        valA = 0;
        valB = 0;
    end

    reg [63:0] registers [0:14];
    integer i;
    initial begin
        for(i = 0; i <= 14; i=i+1) begin
            registers[i] = i;
        end
    end

    always @(*) begin
        if (icode == 4'b0000) begin // halt
        end
        else if (icode == 4'b0001) begin // nop
        end
        else if (icode == 4'b0010) begin // cmovXX
            valA = registers[rA];
        end
        else if (icode == 4'b0011) begin // irmovq
            valB = registers[rB];
        end
        else if (icode == 4'b0100) begin // rmmovq
            valA = registers[rA];
            valB = registers[rB];
        end
        else if (icode == 4'b0101) begin // mrmovq
            valB = registers[rB];
        end
        else if (icode == 4'b0110) begin // OPq
            valA = registers[rA];
            valB = registers[rB];
        end
        else if (icode == 4'b0111) begin // jXX
        end
        else if (icode == 4'b1000) begin // call
            valB = registers[4];
        end
        else if (icode == 4'b1001) begin // ret
            valA = registers[4];
            valB = registers[4];
        end
        else if (icode == 4'b1010) begin // pushq
            valA = registers[rA];
            valB = registers[4];
        end
        else if (icode == 4'b1011) begin // popq
            valA = registers[4];
            valB = registers[4];
        end
    end
endmodule

SEQ/2-decode/2-decode_tb.v
module decode_tb;
    reg clk;
    reg [3:0] icode, rA, rB;
    output [63:0] valA, valB;

    SEQdecode DUT(clk, icode, rA, rB, valA, valB);
    initial begin
        $dumpfile("2-decode.vcd");
        $dumpvars(0, decode_tb);
        clk = 0;

        icode = 4'b0010; rA = 0; 
        #10 clk = ~clk; 
        #10 clk = ~clk;
        icode = 4'b0011; rB = 14; 
        #10 clk = ~clk; 
        #10 clk = ~clk;
        icode = 4'b0100; rA = 1; rB = 13; 
        #10 clk = ~clk; 
        #10 clk = ~clk;
        icode = 4'b0101; rB = 12; 
        #10 clk = ~clk; 
        #10 clk = ~clk;
        icode = 4'b0110; rA = 2; rB = 11; 
        #10 clk = ~clk; 
        #10 clk = ~clk;
        icode = 4'b1000; rB = 10; 
        #10 clk = ~clk; 
        #10 clk = ~clk;
        icode = 4'b1001; rA = 3; rB = 9; 
        #10 clk = ~clk; 
        #10 clk = ~clk;
        icode = 4'b1010; rA = 4; 
        #10 clk = ~clk; 
        #10 clk = ~clk;
        icode = 4'b1011; rA = 5; rB = 8; 
        #10 clk = ~clk; 
        #10 clk = ~clk;
        
    end

    initial
        	$monitor("clk = %0d \tvalA = %0d \tvalB = %0d \n",clk,valA, valB);
endmodule

SEQ/2-decode/2-decode.vcd
$date
	Thu Feb 23 18:38:44 2023
$end
$version
	Icarus Verilog
$end
$timescale
	1s
$end
$scope module decode_tb $end
$var wire 64 ! valB [63:0] $end
$var wire 64 " valA [63:0] $end
$var reg 1 # clk $end
$var reg 4 $ icode [3:0] $end
$var reg 4 % rA [3:0] $end
$var reg 4 & rB [3:0] $end
$scope module DUT $end
$var wire 1 # clk $end
$var wire 4 ' icode [3:0] $end
$var wire 4 ( rA [3:0] $end
$var wire 4 ) rB [3:0] $end
$var reg 64 * valA [63:0] $end
$var reg 64 + valB [63:0] $end
$var integer 32 , i [31:0] $end
$upscope $end
$upscope $end
$enddefinitions $end
#0
$dumpvars
b1111 ,
b0 +
b0 *
bx )
b0 (
b10 '
bx &
b0 %
b10 $
0#
b0 "
b0 !
$end
#10
1#
#20
b1110 &
b1110 )
b11 $
b11 '
0#
#30
b1110 !
b1110 +
1#
#40
b1101 &
b1101 )
b1 %
b1 (
b100 $
b100 '
0#
#50
b1101 !
b1101 +
b1 "
b1 *
1#
#60
b1100 &
b1100 )
b101 $
b101 '
0#
#70
b1100 !
b1100 +
1#
#80
b1011 &
b1011 )
b10 %
b10 (
b110 $
b110 '
0#
#90
b1011 !
b1011 +
b10 "
b10 *
1#
#100
b1010 &
b1010 )
b1000 $
b1000 '
0#
#110
b100 !
b100 +
1#
#120
b1001 &
b1001 )
b11 %
b11 (
b1001 $
b1001 '
0#
#130
b100 "
b100 *
1#
#140
b100 %
b100 (
b1010 $
b1010 '
0#
#150
1#
#160
b1000 &
b1000 )
b101 %
b101 (
b1011 $
b1011 '
0#
