SEQ/6-PCupdate/6-PCupdate.v
module SEQPCupdate(clk, PC, icode, cnd, valC, valM, valP, newPC);
    input clk, cnd;
    input [3:0] icode;
    input [63:0] PC, valC, valM, valP;
    output reg [63:0] newPC;
    always @(*) begin
        if (icode == 4'b0111) begin // jXX
            newPC = (cnd == 1) ? valC : valP;
        end
        else if (icode == 4'b1000) begin // call
            newPC = valC;
        end
        else if (icode == 4'b1001) begin // ret
            newPC = valM;
        end
        else begin // all other instructions
            newPC = valP;
        end
    end
endmodule

SEQ/6-PCupdate/6-PCupdate_tb.v
module PCupdate_tb;
    reg clk, cnd;
    reg [3:0] icode;
    reg [63:0] PC, valC, valM, valP;
    output [63:0] newPC;

    SEQPCupdate DUT(clk, PC, icode, cnd, valC, valM, valP, newPC);
    initial begin
        $dumpfile("6-PCupdate.vcd");
        $dumpvars(0, PCupdate_tb);
        clk = 0;
        PC = 0;

        icode = 4'b0011; valC = 10; valM = 20; valP = 30; cnd = 0;
        #10 clk = ~clk; 
        #10 clk = ~clk;
        icode = 4'b0101; valC = 10; valM = 20; valP = 30; cnd = 0;
        #10 clk = ~clk; 
        #10 clk = ~clk;
        icode = 4'b1000; valC = 10; valM = 20; valP = 30; cnd = 0;
        #10 clk = ~clk; 
        #10 clk = ~clk;
        icode = 4'b1001; valC = 10; valM = 20; valP = 30; cnd = 0;
        #10 clk = ~clk; 
        #10 clk = ~clk;
        icode = 4'b0111; valC = 10; valM = 20; valP = 30; cnd = 0;
        #10 clk = ~clk; 
        #10 clk = ~clk;
        icode = 4'b0111; valC = 10; valM = 20; valP = 30; cnd = 1;
        #10 clk = ~clk; 
        #10 clk = ~clk;
        $finish;
    end

    initial
        	$monitor("clk = %0d \tNew PC = %0b (%0d)\n",clk,newPC, newPC);
endmodule

SEQ/6-PCupdate/6-PCupdate.vcd
$date
	Mon Feb 20 18:36:32 2023
$end
$version
	Icarus Verilog
$end
$timescale
	1s
$end
$scope module PCupdate_tb $end
$var wire 64 ! newPC [63:0] $end
$var reg 64 " PC [63:0] $end
$var reg 1 # clk $end
$var reg 1 $ cnd $end
$var reg 4 % icode [3:0] $end
$var reg 64 & valC [63:0] $end
$var reg 64 ' valM [63:0] $end
$var reg 64 ( valP [63:0] $end
$scope module DUT $end
$var wire 64 ) PC [63:0] $end
$var wire 1 # clk $end
$var wire 1 $ cnd $end
$var wire 4 * icode [3:0] $end
$var wire 64 + valC [63:0] $end
$var wire 64 , valM [63:0] $end
$var wire 64 - valP [63:0] $end
$var reg 64 . newPC [63:0] $end
$upscope $end
$upscope $end
$enddefinitions $end
#0
$dumpvars
bx .
b11110 -
b10100 ,
b1010 +
b11 *
b0 )
b11110 (
b10100 '
b1010 &
b11 %
0$
0#
b0 "
bx !
$end
#10
b11110 !
b11110 .
1#
#20
b101 %
b101 *
0#
#30
1#
#40
b1000 %
b1000 *
0#
#50
b1010 !
b1010 .
1#
#60
b1001 %
b1001 *
0#
#70
b10100 !
b10100 .
1#
#80
b111 %
b111 *
0#
#90
b11110 !
b11110 .
1#
#100
1$
0#
#110
b1010 !
b1010 .
1#
