ALU/AND/and-64.v
`timescale 10ns/1ns
module and64(input signed [63:0]a, input signed [63:0]b, output signed [63:0] ans);
    genvar i;
    for(i = 0; i < 64; i=i+1)
    begin
        and G1(ans[i], a[i], b[i]);
    end
endmodule

ALU/AND/and-testbench.v
`timescale 10ns/1ns
module testbench;
    reg signed [63:0] a;
    reg signed [63:0] b;
    wire signed [63:0] ans;
    and64 DUT(a,b,ans);
    initial
    begin
        $dumpfile("and-dump.vcd");
        $dumpvars(0, testbench);
        a = 64'b0; b = 64'b0;
        #10;
        #2 a = 64'b110101010101001010101010; b = 64'b10100101010111010111010;
        #2 a = 64'b010101000011010111011001; b = 64'b1111000101011100000110;
        #2 a = 64'b111101001010001001011010; b = 64'b111100111011001101111011;
        #2 a = 587619328768; b = 9923145637281;
        #2 a = -78382942; b = -35682899912;
        #2 a = $random; b = $random;
        #2 a = $random; b = $random;
        #2 a = $random; b = $random;
        #2 a = $random; b = $random;
        #2 a = $random; b = $random;
        #2 a = $random; b = $random;
        #2 $finish;
    end
    initial
        $monitor ("A = %0d, B = %0d -> Ans = %0d\nA   = %b\nB   = %b\nAns = %b\n", a,b,ans,a,b,ans);
endmodule

ALU/AND/and-dump.vcd
$date
	Sat Jan 21 07:47:23 2023
$end
$version
	Icarus Verilog
$end
$timescale
	1ns
$end
$scope module testbench $end
$var wire 64 ! ans [63:0] $end
$var reg 64 " a [63:0] $end
$var reg 64 # b [63:0] $end
$scope module DUT $end
$var wire 64 $ a [63:0] $end
$var wire 64 % b [63:0] $end
$var wire 64 & ans [63:0] $end
$scope begin genblk1[0] $end
$upscope $end
$scope begin genblk1[1] $end
$upscope $end
$scope begin genblk1[2] $end
$upscope $end
$scope begin genblk1[3] $end
$upscope $end
$scope begin genblk1[4] $end
$upscope $end
$scope begin genblk1[5] $end
$upscope $end
$scope begin genblk1[6] $end
$upscope $end
$scope begin genblk1[7] $end
$upscope $end
$scope begin genblk1[8] $end
$upscope $end
$scope begin genblk1[9] $end
$upscope $end
$scope begin genblk1[10] $end
$upscope $end
$scope begin genblk1[11] $end
$upscope $end
$scope begin genblk1[12] $end
$upscope $end
$scope begin genblk1[13] $end
$upscope $end
$scope begin genblk1[14] $end
$upscope $end
$scope begin genblk1[15] $end
$upscope $end
$scope begin genblk1[16] $end
$upscope $end
$scope begin genblk1[17] $end
$upscope $end
$scope begin genblk1[18] $end
$upscope $end
$scope begin genblk1[19] $end
$upscope $end
$scope begin genblk1[20] $end
$upscope $end
$scope begin genblk1[21] $end
$upscope $end
$scope begin genblk1[22] $end
$upscope $end
$scope begin genblk1[23] $end
$upscope $end
$scope begin genblk1[24] $end
$upscope $end
$scope begin genblk1[25] $end
$upscope $end
$scope begin genblk1[26] $end
$upscope $end
$scope begin genblk1[27] $end
$upscope $end
$scope begin genblk1[28] $end
$upscope $end
$scope begin genblk1[29] $end
$upscope $end
$scope begin genblk1[30] $end
$upscope $end
$scope begin genblk1[31] $end
$upscope $end
$scope begin genblk1[32] $end
$upscope $end
$scope begin genblk1[33] $end
$upscope $end
$scope begin genblk1[34] $end
$upscope $end
$scope begin genblk1[35] $end
$upscope $end
$scope begin genblk1[36] $end
$upscope $end
$scope begin genblk1[37] $end
$upscope $end
$scope begin genblk1[38] $end
$upscope $end
$scope begin genblk1[39] $end
$upscope $end
$scope begin genblk1[40] $end
$upscope $end
$scope begin genblk1[41] $end
$upscope $end
$scope begin genblk1[42] $end
$upscope $end
$scope begin genblk1[43] $end
$upscope $end
$scope begin genblk1[44] $end
$upscope $end
$scope begin genblk1[45] $end
$upscope $end
$scope begin genblk1[46] $end
$upscope $end
$scope begin genblk1[47] $end
$upscope $end
$scope begin genblk1[48] $end
$upscope $end
$scope begin genblk1[49] $end
$upscope $end
$scope begin genblk1[50] $end
$upscope $end
$scope begin genblk1[51] $end
$upscope $end
$scope begin genblk1[52] $end
$upscope $end
$scope begin genblk1[53] $end
$upscope $end
$scope begin genblk1[54] $end
$upscope $end
$scope begin genblk1[55] $end
$upscope $end
$scope begin genblk1[56] $end
$upscope $end
$scope begin genblk1[57] $end
$upscope $end
$scope begin genblk1[58] $end
$upscope $end
$scope begin genblk1[59] $end
$upscope $end
$scope begin genblk1[60] $end
$upscope $end
$scope begin genblk1[61] $end
$upscope $end
$scope begin genblk1[62] $end
$upscope $end
$scope begin genblk1[63] $end
$upscope $end
$upscope $end
$upscope $end
$enddefinitions $end
#0
$dumpvars
b0 &
b0 %
b0 $
b0 #
b0 "
b0 !
$end
#120
b10100000000001010101010 !
b10100000000001010101010 &
b10100101010111010111010 #
b10100101010111010111010 %
b110101010101001010101010 "
b110101010101001010101010 $
#140
b101000001010100000000 !
b101000001010100000000 &
b1111000101011100000110 #
b1111000101011100000110 %
b10101000011010111011001 "
b10101000011010111011001 $
#160
b111100001010001001011010 !
b111100001010001001011010 &
b111100111011001101111011 #
b111100111011001101111011 %
b111101001010001001011010 "
b111101001010001001011010 $
#180
b1000000100100100000000100000000 !
b1000000100100100000000100000000 &
b10010000011001101001100100100001110110100001 #
b10010000011001101001100100100001110110100001 %
b1000100011010000110101110110001100000000 "
b1000100011010000110101110110001100000000 $
#200
b1111111111111111111111111111011110110001000000100010100000100000 !
b1111111111111111111111111111011110110001000000100010100000100000 &
b1111111111111111111111111111011110110001001000100010100000111000 #
b1111111111111111111111111111011110110001001000100010100000111000 %
b1111111111111111111111111111111111111011010100111111100010100010 "
b1111111111111111111111111111111111111011010100111111100010100010 $
#220
b10001010000000000 !
b10001010000000000 &
b1111111111111111111111111111111111000000100010010101111010000001 #
b1111111111111111111111111111111111000000100010010101111010000001 %
b10010000101010011010100100100 "
b10010000101010011010100100100 $
#240
b1111111111111111111111111111111110000000100000000101011000000001 !
b1111111111111111111111111111111110000000100000000101011000000001 &
b1111111111111111111111111111111110110001111100000101011001100011 #
b1111111111111111111111111111111110110001111100000101011001100011 %
b1111111111111111111111111111111110000100100001001101011000001001 "
b1111111111111111111111111111111110000100100001001101011000001001 $
#260
b110100110010001100100001101 !
b110100110010001100100001101 &
b1000110110111111001100110001101 #
b1000110110111111001100110001101 %
b110101110010111101100001101 "
b110101110010111101100001101 $
#280
b1111111111111111111111111111111110000000000000100000000000000000 !
b1111111111111111111111111111111110000000000000100000000000000000 &
b1111111111111111111111111111111110001001001101110101001000010010 #
b1111111111111111111111111111111110001001001101110101001000010010 %
b1111111111111111111111111111111110110010110000101000010001100101 "
b1111111111111111111111111111111110110010110000101000010001100101 $
#300
b110100111100000100000001 !
b110100111100000100000001 &
b110110101111100110100001101 #
b110110101111100110100001101 %
b111100111110001100000001 "
b111100111110001100000001 $
#320
b11010000000011100000100110100 !
b11010000000011100000100110100 &
b11110100011011100110100111101 #
b11110100011011100110100111101 %
b111011001000111111000101110110 "
b111011001000111111000101110110 $
