SEQ/1-fetch/1-fetch.v
module SEQfetch(clk, PC, icode, ifun, rA, rB, valC, valP, hlt, mem_error, instr_valid);
    input clk;
    input [63:0] PC;
    output reg hlt, mem_error, instr_valid;
    output reg [3:0] icode, ifun, rA, rB;
    output reg [63:0] valC, valP;

    initial begin
        rA = 4'hF;
        rB = 4'hF;
        valC = 0;
        valP = 0;
        hlt = 0;
        mem_error = 0;
        instr_valid = 1;
    end

    reg [7:0] instr_memory [0:1023];
    initial begin
        instr_memory[0]  = 8'b00010000; // nop

        instr_memory[1]  = 8'b01100000; // OPq ADD
        instr_memory[2]  = 8'b00000001; // rA = 0, rB = 1

        instr_memory[3]  = 8'b00110000; // irmovq 
        instr_memory[4]  = 8'b11110010; // F, rB = 2;
        instr_memory[5]  = 8'b11111111; // 1st byte
        instr_memory[6]  = 8'b00000000; // 2nd byte
        instr_memory[7]  = 8'b00000000; // 3rd byte
        instr_memory[8]  = 8'b00000000; // 4th byte
        instr_memory[9]  = 8'b00000000; // 5th byte
        instr_memory[10] = 8'b00000000; // 6th byte
        instr_memory[11] = 8'b00000000; // 7th byte
        instr_memory[12] = 8'b00000000; // 8th byte

        instr_memory[13] = 8'b00110000; // irmovq instruction
        instr_memory[14] = 8'b11110011; // F, rB = 3;
        instr_memory[15] = 8'b00000101; // 1st byte
        instr_memory[16] = 8'b00000000; // 2nd byte
        instr_memory[17] = 8'b00000000; // 3rd byte
        instr_memory[18] = 8'b00000000; // 4th byte
        instr_memory[19] = 8'b00000000; // 5th byte
        instr_memory[20] = 8'b00000000; // 6th byte
        instr_memory[21] = 8'b00000000; // 7th byte
        instr_memory[22] = 8'b00000000; // 8th byte

        instr_memory[23] = 8'b00100000; // rrmovq
        instr_memory[24] = 8'b01000101; // rA = 4, rB = 5

        instr_memory[25] = 8'b01100010; // OPq AND 
        instr_memory[26] = 8'b00110100; // rA = 3, rB = 4

        instr_memory[27] = 8'b00100101; // cmovge
        instr_memory[28] = 8'b01010110; // rA = 5; rB = 6;

        instr_mem[29]=8'b10000000; //8 0
        instr_mem[30]=8'b00000000; //Dest
        instr_mem[31]=8'b00000000; //Dest
        instr_mem[32]=8'b00000000; //Dest
        instr_mem[33]=8'b00000000; //Dest
        instr_mem[34]=8'b00000000; //Dest
        instr_mem[35]=8'b00000000; //Dest
        instr_mem[36]=8'b00000000; //Dest
        instr_mem[37]=8'b00000001; //Dest

        instr_mem[38]=8'b10010000; // 9 0

        instr_memory[39] = 8'b00000000; // halt
    end

    reg [7:0] opcode, regids;
    
    always @(*) begin
        if (PC > 1023) begin
            mem_error = 1;
        end
        opcode = instr_memory[PC];
        icode = opcode[7:4];
        ifun = opcode[3:0];
        if (icode == 4'b0000) begin // halt
            hlt = 1;
            valP = PC+1;
        end
        else if (icode == 4'b0001) begin // nop
            valP = PC+1;
        end
        else if (icode == 4'b0010) begin // cmovXX
            regids = instr_memory[PC+1];
            rA = regids[7:4];
            rB = regids[3:0];
            valP = PC+2;
        end
        else if (icode == 4'b0011) begin // irmovq
            regids = instr_memory[PC+1];
            rA = regids[7:4];
            rB = regids[3:0];
            valC = {instr_memory[PC+9], instr_memory[PC+8], instr_memory[PC+7], instr_memory[PC+6], instr_memory[PC+5], instr_memory[PC+4], instr_memory[PC+3], instr_memory[PC+2]};
            valP = PC+10;
        end
        else if (icode == 4'b0100) begin // rmmovq
            regids = instr_memory[PC+1];
            rA = regids[7:4];
            rB = regids[3:0];
            valC = {instr_memory[PC+9], instr_memory[PC+8], instr_memory[PC+7], instr_memory[PC+6], instr_memory[PC+5], instr_memory[PC+4], instr_memory[PC+3], instr_memory[PC+2]};
            valP = PC+10;
        end
        else if (icode == 4'b0101) begin // mrmovq
            regids = instr_memory[PC+1];
            rA = regids[7:4];
            rB = regids[3:0];
            valC = {instr_memory[PC+9], instr_memory[PC+8], instr_memory[PC+7], instr_memory[PC+6], instr_memory[PC+5], instr_memory[PC+4], instr_memory[PC+3], instr_memory[PC+2]};
            valP = PC+10;
        end
        else if (icode == 4'b0110) begin // OPq
            regids = instr_memory[PC+1];
            rA = regids[7:4];
            rB = regids[3:0];
            valP = PC+2;
        end
        else if (icode == 4'b0111) begin // jXX
            valC = {instr_memory[PC+8], instr_memory[PC+7], instr_memory[PC+6], instr_memory[PC+5], instr_memory[PC+4], instr_memory[PC+3], instr_memory[PC+2], instr_memory[PC+1]};
            valP = PC+9;
        end
        else if (icode == 4'b1000) begin // call
            valC = {instr_memory[PC+8], instr_memory[PC+7], instr_memory[PC+6], instr_memory[PC+5], instr_memory[PC+4], instr_memory[PC+3], instr_memory[PC+2], instr_memory[PC+1]};
            valP = PC+9;
        end
        else if (icode == 4'b1001) begin // ret
            valP = PC+1;
        end
        else if (icode == 4'b1010) begin // pushq
            regids = instr_memory[PC+1];
            rA = regids[7:4];
            rB = regids[3:0];
            valP = PC+2;
        end
        else if (icode == 4'b1011) begin // popq
            regids = instr_memory[PC+1];
            rA = regids[7:4];
            rB = regids[3:0];
            valP = PC+2;
        end
        else begin 
            instr_valid = 0;
        end
    end
endmodule

SEQ/1-fetch/1-fetch_tb.v
module fetch_tb;
    reg clk;
    reg [63:0] PC;
    wire hlt, mem_error, instr_valid;
    wire [3:0] icode, ifun, rA, rB;
    wire [63:0] valC, valP;

    SEQfetch DUT(clk, PC, icode, ifun, rA, rB, valC, valP, hlt, mem_error, instr_valid);
    initial begin
        $dumpfile("1-fetch.vcd");
        $dumpvars(0, fetch_tb);
        clk = 0;
        PC = 0;

        #10 clk=~clk;
        #10 clk=~clk;PC=valP;
        #10 clk=~clk;
        #10 clk=~clk;PC=valP;
        #10 clk=~clk;
        #10 clk=~clk;PC=valP;
        #10 clk=~clk;
        #10 clk=~clk;PC=valP;
        #10 clk=~clk;
        #10 clk=~clk;PC=valP;
        #10 clk=~clk;
        #10 clk=~clk;PC=valP;
        #10 clk=~clk;
        #10 clk=~clk;PC=valP;
        #10 clk=~clk;
        #10 clk=~clk;PC=valP;
        #10 clk=~clk;
        #10 clk=~clk;PC=valP;
        #10 clk=~clk;
        #10 clk=~clk;PC=valP;
        #10 clk=~clk;
        #10 clk=~clk;PC=valP;
        $finish;
    end

    initial
    		$monitor("clk = %0d \tPC = %0b (%0d)\ticode=%0b (%0d)\tifun=%0b (%0d)\nrA=%0b (%0d)\trB=%0b (%0d)\tvalC=%0d \tvalP=%0d\nhlt = %0d \tinstr_valid = %0d \tmem_error = %0d\n",clk,PC,PC,icode,icode,ifun,ifun,rA,rA,rB,rB,valC,valP,hlt,instr_valid,mem_error);
endmodule

SEQ/1-fetch/1-fetch.vcd
$date
	Wed Mar  8 19:21:24 2023
$end
$version
	Icarus Verilog
$end
$timescale
	1s
$end
$scope module fetch_tb $end
$var wire 64 ! valP [63:0] $end
$var wire 64 " valC [63:0] $end
$var wire 4 # rB [3:0] $end
$var wire 4 $ rA [3:0] $end
$var wire 1 % mem_error $end
$var wire 1 & instr_valid $end
$var wire 4 ' ifun [3:0] $end
$var wire 4 ( icode [3:0] $end
$var wire 1 ) hlt $end
$var reg 64 * PC [63:0] $end
$var reg 1 + clk $end
$scope module DUT $end
$var wire 64 , PC [63:0] $end
$var wire 1 + clk $end
$var reg 1 ) hlt $end
$var reg 4 - icode [3:0] $end
$var reg 4 . ifun [3:0] $end
$var reg 1 & instr_valid $end
$var reg 1 % mem_error $end
$var reg 8 / opcode [7:0] $end
$var reg 4 0 rA [3:0] $end
$var reg 4 1 rB [3:0] $end
$var reg 8 2 regids [7:0] $end
$var reg 64 3 valC [63:0] $end
$var reg 64 4 valP [63:0] $end
$upscope $end
$upscope $end
$enddefinitions $end
#0
$dumpvars
b0 4
b0 3
bx 2
b1111 1
b1111 0
bx /
bx .
bx -
b0 ,
0+
b0 *
0)
bx (
bx '
1&
0%
b1111 $
b1111 #
b0 "
b0 !
$end
#10
b1 !
b1 4
b0 '
b0 .
b1 (
b1 -
b10000 /
1+
#20
b1 *
b1 ,
0+
#30
b11 !
b11 4
b1 #
b1 1
b0 $
b0 0
b1 2
b110 (
b110 -
b1100000 /
1+
#40
b11 *
b11 ,
0+
#50
b1101 !
b1101 4
b11111111 "
b11111111 3
b10 #
b10 1
b1111 $
b1111 0
b11110010 2
b11 (
b11 -
b110000 /
1+
#60
b1101 *
b1101 ,
0+
#70
b10111 !
b10111 4
b101 "
b101 3
b11 #
b11 1
b11110011 2
1+
#80
b10111 *
b10111 ,
0+
#90
b11001 !
b11001 4
b101 #
b101 1
b100 $
b100 0
b1000101 2
b10 (
b10 -
b100000 /
1+
#100
b11001 *
b11001 ,
0+
#110
b11011 !
b11011 4
b100 #
b100 1
b11 $
b11 0
b110100 2
b10 '
b10 .
b110 (
b110 -
b1100010 /
1+
#120
b11011 *
b11011 ,
0+
#130
b11101 !
b11101 4
b110 #
b110 1
b101 $
b101 0
b1010110 2
b101 '
b101 .
b10 (
b10 -
b100101 /
1+
#140
b11101 *
b11101 ,
0+
#150
b100110 !
b100110 4
b100111 "
b100111 3
b0 '
b0 .
b111 (
b111 -
b1110000 /
1+
#160
b100110 *
b100110 ,
0+
#170
b100111 !
b100111 4
b1 (
b1 -
b10000 /
1+
#180
b100111 *
b100111 ,
0+
#190
b101001 !
b101001 4
b101 #
b101 1
b11 $
b11 0
b110101 2
b110 (
b110 -
b1100000 /
1+
#200
b101001 *
b101001 ,
0+
#210
b101010 !
b101010 4
1)
b0 (
b0 -
b0 /
1+
#220
b101010 *
b101010 ,
0+
